visual_testify/__init__.py
visual_testify/visual_assertion.py
pytest_vtestify-0.2.1.dist-info/LICENSE
pytest_vtestify-0.2.1.dist-info/METADATA
pytest_vtestify-0.2.1.dist-info/WHEEL
pytest_vtestify-0.2.1.dist-info/entry_points.txt
pytest_vtestify-0.2.1.dist-info/top_level.txt
pytest_vtestify-0.2.1.dist-info/RECORD
