Metadata-Version: 2.2
Name: pytest-vtestify
Version: 0.2.1
Summary: A pytest plugin for visual assertion using SSIM and image comparison.
Home-page: https://github.com/idejongkok/pytest-vtestify
Author: Aria Uno Suseno
Author-email: idejongkok@gmail.com
Project-URL: Documentation, https://vtestify.idejongkok.com
Project-URL: Source, https://github.com/idejongkok/pytest-vtestify
Classifier: Programming Language :: Python :: 3
Classifier: License :: OSI Approved :: MIT License
Classifier: Operating System :: OS Independent
Classifier: Framework :: Pytest
Requires-Python: >=3.11
License-File: LICENSE
Requires-Dist: pytest
Requires-Dist: opencv-python
Requires-Dist: scikit-image
Requires-Dist: numpy
Dynamic: author
Dynamic: author-email
Dynamic: classifier
Dynamic: description
Dynamic: description-content-type
Dynamic: home-page
Dynamic: project-url
Dynamic: requires-dist
Dynamic: requires-python
Dynamic: summary
